{
  "generator-jhipster": {
    "blueprints": [],
    "otherModules": [],
    "applicationType": "microservice",
    "baseName": "WaterBilling",
    "jhipsterVersion": "7.0.1",
    "skipClient": true,
    "skipUserManagement": true,
    "skipServer": false,
    "skipCheckLengthOfIdentifier": false,
    "skipFakeData": false,
    "jhiPrefix": "jhi",
    "entitySuffix": "",
    "dtoSuffix": "DTO",
    "testFrameworks": [],
    "pages": [],
    "creationTimestamp": 1628877299920,
    "serviceDiscoveryType": "eureka",
    "reactive": false,
    "authenticationType": "jwt",
    "packageName": "ke.co.macoz.realestate.waterbilling",
    "serverPort": "8081",
    "cacheProvider": "hazelcast",
    "enableHibernateCache": true,
    "databaseType": "sql",
    "devDatabaseType": "h2Disk",
    "prodDatabaseType": "postgresql",
    "buildTool": "maven",
    "serverSideOptions": [],
    "websocket": false,
    "searchEngine": false,
    "messageBroker": false,
    "enableSwaggerCodegen": false,
    "enableTranslation": false,
    "nativeLanguage": "en",
    "packageFolder": "ke/co/macoz/realestate/waterbilling",
    "jwtSecretKey": "ZmQ1MjA1ZDAzM2ZiYTVkZjhkNGRhYWNhZWFiYjRmYmNjMDdkZmRmNGQ2NzkyYTIzYjQ4M2FhNTk0ODNmNDE5YzlmMjM1YzBhYjRmYTUzMTQ3OTNhNWUxNWE5ZDQ2NjZkOWI4NDRmNDZjNjkxODlhODNiODhmN2EwMmQxNWFmODQ=",
    "languages": ["en", "fr"]
  }
}
